[
  {
    "verse": 1,
    "reference": "Psalm 127:1",
    "text": "Unless the Lord builds the house,\n  They labor in vain who build it;\n  Unless the Lord guards the city,\n  The watchman keeps awake in vain."
  },
  {
    "verse": 2,
    "reference": "Psalm 127:2",
    "text": "It is vain for you to rise up early,\n  To retire late,\n  To eat the bread of painful labors;\n  For He gives to His beloved even in his sleep."
  },
  {
    "verse": 3,
    "reference": "Psalm 127:3",
    "text": "Behold, children are a gift of the Lord,\n  The fruit of the womb is a reward."
  },
  {
    "verse": 4,
    "reference": "Psalm 127:4",
    "text": "Like arrows in the hand of a warrior,\n  So are the children of one’s youth."
  },
  {
    "verse": 5,
    "reference": "Psalm 127:5",
    "text": "How blessed is the man whose quiver is full of them;\n  They will not be ashamed\n  When they speak with their enemies in the gate."
  }
]